{
  "resourceType" : "CodeSystem",
  "id" : "b1ab6d48-34a5-4a3b-a66e-ed4e3c78891e-20",
  "url" : "http://hl7.org/fhir/comparison/CodeSystem/b1ab6d48-34a5-4a3b-a66e-ed4e3c78891e-20",
  "name" : "UnionEclaireStudyPhaseCSAndEclaireStudyPhaseCS",
  "title" : "Union of Définition des type de phase de l'essai cliniques incluant https://hl7.org/fhir/R4/valueset-research-study-phase.html And Définition des type de phase de l'essai cliniques incluant https://hl7.org/fhir/R4/valueset-research-study-phase.html",
  "status" : "draft",
  "date" : "2025-05-20T16:41:33+00:00",
  "jurisdiction" : [{
    "coding" : [{
      "system" : "urn:iso:std:iso:3166",
      "code" : "FR",
      "display" : "FRANCE"
    }]
  }],
  "concept" : [{
    "code" : "phase-3-phase-4",
    "display" : "Phase 3 and phase 4",
    "definition" : "Trials that are a combination of phases 3 and 4."
  }]
}