{
  "resourceType" : "ValueSet",
  "id" : "67270873-899c-4f25-988b-111de614d687-111",
  "url" : "http://hl7.org/fhir/comparison/ValueSet/67270873-899c-4f25-988b-111de614d687-111",
  "name" : "IntersectionEclaireStudyPartyRoleVSAndEclaireStudyPartyRoleVS",
  "title" : "Intersection of Value Set Eclaire pour les différents rôles des parties impliquées dans l'essai And Value Set Eclaire pour les différents rôles des parties impliquées dans l'essai",
  "status" : "draft",
  "date" : "2025-07-15T14:54:51+00:00",
  "jurisdiction" : [{
    "coding" : [{
      "system" : "urn:iso:std:iso:3166",
      "code" : "FR",
      "display" : "FRANCE"
    }]
  }]
}