{
  "resourceType" : "CodeSystem",
  "id" : "349628a1-0e63-4002-903b-80e0b0c27c86-30",
  "url" : "http://hl7.org/fhir/comparison/CodeSystem/349628a1-0e63-4002-903b-80e0b0c27c86-30",
  "name" : "IntersectionEclaireStudyStatusCSAndEclaireStudyStatusCS",
  "title" : "Intersection of Définition des statuts de l'essai utilisés dans la base de données ECLAIRE And Définition des statuts de l'essai utilisés dans la base de données ECLAIRE",
  "status" : "draft",
  "date" : "2025-07-21T14:16:11+00:00",
  "jurisdiction" : [{
    "coding" : [{
      "system" : "urn:iso:std:iso:3166",
      "code" : "FR",
      "display" : "FRANCE"
    }]
  }],
  "concept" : [{
    "code" : "a-demarrer",
    "display" : "A démarrer"
  },
  {
    "code" : "en-cours",
    "display" : "En cours"
  },
  {
    "code" : "suspendue",
    "display" : "Suspendue"
  },
  {
    "code" : "prorogee",
    "display" : "Prorogée"
  },
  {
    "code" : "expiree",
    "display" : "Expirée"
  },
  {
    "code" : "terminee",
    "display" : "Terminée"
  },
  {
    "code" : "terminee-fin-anticipee",
    "display" : "Terminée (fin anticipée)"
  },
  {
    "code" : "archivee",
    "display" : "Archivée"
  },
  {
    "code" : "abandonnee",
    "display" : "Abandonnée"
  }]
}